synthic/__init__.py
synthic-0.1.0.dist-info/METADATA
synthic-0.1.0.dist-info/WHEEL
synthic-0.1.0.dist-info/RECORD
