Metadata-Version: 2.1
Name: synthic
Version: 0.1.0
Summary: Synthetic data generation based on SQLAlchemy models
Author: Pavel.Groshev
Author-email: pavluxa@xmail.ru
Requires-Python: >=3.12,<4.0
Classifier: Programming Language :: Python :: 3
Classifier: Programming Language :: Python :: 3.12
Classifier: Programming Language :: Python :: 3.13
Requires-Dist: faker (>=33.1.0,<34.0.0)
Requires-Dist: mypy (>=1.14.0,<2.0.0)
Requires-Dist: ruff (>=0.8.4,<0.9.0)
Requires-Dist: sqlalchemy (>=2.0.36,<3.0.0)
